{
  "meta": {
    "code": 200
  },
  "response": {
    "holidays": [
      {
        "name": "New Year's Day",
        "description": "New Year’s Day is the first day of the year, or January 1, in the Gregorian calendar.",
        "country": {
          "id": "gt",
          "name": "Guatemala"
        },
        "date": {
          "iso": "2024-01-01",
          "datetime": {
            "year": 2024,
            "month": 1,
            "day": 1
          }
        },
        "type": [
          "National holiday"
        ],
        "primary_type": "National holiday",
        "canonical_url": "https://calendarific.com/holiday/guatemala/new-year-day",
        "urlid": "guatemala/new-year-day",
        "locations": "All",
        "states": "All"
      },
      {
        "name": "March Equinox",
        "description": "March Equinox in Guatemala (Guatemala City)",
        "country": {
          "id": "gt",
          "name": "Guatemala"
        },
        "date": {
          "iso": "2024-03-19T21:06:28-06:00",
          "datetime": {
            "year": 2024,
            "month": 3,
            "day": 19,
            "hour": 21,
            "minute": 6,
            "second": 28
          },
          "timezone": {
            "offset": "-06:00",
            "zoneabb": "CST",
            "zoneoffset": -21600,
            "zonedst": 0,
            "zonetotaloffset": -21600
          }
        },
        "type": [
          "Season"
        ],
        "primary_type": "Season",
        "canonical_url": "https://calendarific.com/holiday/seasons/vernal-equinox",
        "urlid": "seasons/vernal-equinox",
        "locations": "All",
        "states": "All"
      },
      {
        "name": "Maundy Thursday",
        "description": "Maundy Thursday is a Christian observance on the Thursday during Holy Week. It is the day before Good Friday.",
        "country": {
          "id": "gt",
          "name": "Guatemala"
        },
        "date": {
          "iso": "2024-03-28",
          "datetime": {
            "year": 2024,
            "month": 3,
            "day": 28
          }
        },
        "type": [
          "National holiday",
          "Christian"
        ],
        "primary_type": "Christian",
        "canonical_url": "https://calendarific.com/holiday/guatemala/maundy-thursday",
        "urlid": "guatemala/maundy-thursday",
        "locations": "All",
        "states": "All"
      },
      {
        "name": "Good Friday",
        "description": "Good Friday is a global Christian observance two days before Easter Sunday.",
        "country": {
          "id": "gt",
          "name": "Guatemala"
        },
        "date": {
          "iso": "2024-03-29",
          "datetime": {
            "year": 2024,
            "month": 3,
            "day": 29
          }
        },
        "type": [
          "National holiday",
          "Christian"
        ],
        "primary_type": "Christian",
        "canonical_url": "https://calendarific.com/holiday/guatemala/good-friday",
        "urlid": "guatemala/good-friday",
        "locations": "All",
        "states": "All"
      },
      {
        "name": "Easter Saturday",
        "description": "Holy Saturday is the day before Easter Sunday.",
        "country": {
          "id": "gt",
          "name": "Guatemala"
        },
        "date": {
          "iso": "2024-03-30",
          "datetime": {
            "year": 2024,
            "month": 3,
            "day": 30
          }
        },
        "type": [
          "National holiday",
          "Christian"
        ],
        "primary_type": "Christian",
        "canonical_url": "https://calendarific.com/holiday/guatemala/easter-saturday",
        "urlid": "guatemala/easter-saturday",
        "locations": "All",
        "states": "All"
      },
      {
        "name": "Easter Sunday",
        "description": "Easter Sunday commemorates Jesus Christ’s resurrection, according to Christian belief.",
        "country": {
          "id": "gt",
          "name": "Guatemala"
        },
        "date": {
          "iso": "2024-03-31",
          "datetime": {
            "year": 2024,
            "month": 3,
            "day": 31
          }
        },
        "type": [
          "Observance",
          "Christian"
        ],
        "primary_type": "Christian",
        "canonical_url": "https://calendarific.com/holiday/guatemala/easter-sunday",
        "urlid": "guatemala/easter-sunday",
        "locations": "All",
        "states": "All"
      },
      {
        "name": "Easter Monday",
        "description": "Easter Monday is the day after Easter Sunday.",
        "country": {
          "id": "gt",
          "name": "Guatemala"
        },
        "date": {
          "iso": "2024-04-01",
          "datetime": {
            "year": 2024,
            "month": 4,
            "day": 1
          }
        },
        "type": [
          "Observance",
          "Christian"
        ],
        "primary_type": "Christian",
        "canonical_url": "https://calendarific.com/holiday/guatemala/easter-monday",
        "urlid": "guatemala/easter-monday",
        "locations": "All",
        "states": "All"
      },
      {
        "name": "Labor Day",
        "description": "Labor Day, International Workers' Day, and May Day, is a day off for workers in many countries around the world.",
        "country": {
          "id": "gt",
          "name": "Guatemala"
        },
        "date": {
          "iso": "2024-05-01",
          "datetime": {
            "year": 2024,
            "month": 5,
            "day": 1
          }
        },
        "type": [
          "National holiday"
        ],
        "primary_type": "National holiday",
        "canonical_url": "https://calendarific.com/holiday/guatemala/labor-day",
        "urlid": "guatemala/labor-day",
        "locations": "All",
        "states": "All"
      },
      {
        "name": "Mothers’ Day (Working Mothers Only)",
        "description": "Mother’s Day celebrates the achievements and efforts of mothers and mother figures.",
        "country": {
          "id": "gt",
          "name": "Guatemala"
        },
        "date": {
          "iso": "2024-05-10",
          "datetime": {
            "year": 2024,
            "month": 5,
            "day": 10
          }
        },
        "type": [
          "National holiday"
        ],
        "primary_type": "National holiday",
        "canonical_url": "https://calendarific.com/holiday/guatemala/mothers-day",
        "urlid": "guatemala/mothers-day",
        "locations": "All",
        "states": "All"
      },
      {
        "name": "June Solstice",
        "description": "June Solstice in Guatemala (Guatemala City)",
        "country": {
          "id": "gt",
          "name": "Guatemala"
        },
        "date": {
          "iso": "2024-06-20T14:50:59-06:00",
          "datetime": {
            "year": 2024,
            "month": 6,
            "day": 20,
            "hour": 14,
            "minute": 50,
            "second": 59
          },
          "timezone": {
            "offset": "-06:00",
            "zoneabb": "CST",
            "zoneoffset": -21600,
            "zonedst": 0,
            "zonetotaloffset": -21600
          }
        },
        "type": [
          "Season"
        ],
        "primary_type": "Season",
        "canonical_url": "https://calendarific.com/holiday/seasons/june-solstice",
        "urlid": "seasons/june-solstice",
        "locations": "All",
        "states": "All"
      },
      {
        "name": "Army Day",
        "description": "Army Day is a observance in Guatemala",
        "country": {
          "id": "gt",
          "name": "Guatemala"
        },
        "date": {
          "iso": "2024-06-30",
          "datetime": {
            "year": 2024,
            "month": 6,
            "day": 30
          }
        },
        "type": [
          "Observance"
        ],
        "primary_type": "Observance",
        "canonical_url": "https://calendarific.com/holiday/guatemala/army-day",
        "urlid": "guatemala/army-day",
        "locations": "All",
        "states": "All"
      },
      {
        "name": "Army Day Holiday",
        "description": "Army Day Holiday is a national holiday in Guatemala",
        "country": {
          "id": "gt",
          "name": "Guatemala"
        },
        "date": {
          "iso": "2024-07-01",
          "datetime": {
            "year": 2024,
            "month": 7,
            "day": 1
          }
        },
        "type": [
          "National holiday"
        ],
        "primary_type": "National holiday",
        "canonical_url": "https://calendarific.com/holiday/guatemala/army-day",
        "urlid": "guatemala/army-day",
        "locations": "All",
        "states": "All"
      },
      {
        "name": "Assumption of Mary (Guatemala City only)",
        "description": "The Christian feast of the Assumption of Mary is on or around Aug 15 in most countries. A few celebrate Assumption Day at other times of the year.",
        "country": {
          "id": "gt",
          "name": "Guatemala"
        },
        "date": {
          "iso": "2024-08-15",
          "datetime": {
            "year": 2024,
            "month": 8,
            "day": 15
          }
        },
        "type": [
          "Local holiday"
        ],
        "primary_type": "Municipal holiday",
        "canonical_url": "https://calendarific.com/holiday/guatemala/assumption-day",
        "urlid": "guatemala/assumption-day",
        "locations": "All",
        "states": "All"
      },
      {
        "name": "Independence Day",
        "description": "Independence Day is a national holiday in Guatemala",
        "country": {
          "id": "gt",
          "name": "Guatemala"
        },
        "date": {
          "iso": "2024-09-15",
          "datetime": {
            "year": 2024,
            "month": 9,
            "day": 15
          }
        },
        "type": [
          "National holiday"
        ],
        "primary_type": "National holiday",
        "canonical_url": "https://calendarific.com/holiday/guatemala/independence-day",
        "urlid": "guatemala/independence-day",
        "locations": "All",
        "states": "All"
      },
      {
        "name": "September Equinox",
        "description": "September Equinox in Guatemala (Guatemala City)",
        "country": {
          "id": "gt",
          "name": "Guatemala"
        },
        "date": {
          "iso": "2024-09-22T06:43:33-06:00",
          "datetime": {
            "year": 2024,
            "month": 9,
            "day": 22,
            "hour": 6,
            "minute": 43,
            "second": 33
          },
          "timezone": {
            "offset": "-06:00",
            "zoneabb": "CST",
            "zoneoffset": -21600,
            "zonedst": 0,
            "zonetotaloffset": -21600
          }
        },
        "type": [
          "Season"
        ],
        "primary_type": "Season",
        "canonical_url": "https://calendarific.com/holiday/seasons/autumnal-equniox",
        "urlid": "seasons/autumnal-equniox",
        "locations": "All",
        "states": "All"
      },
      {
        "name": "Dia de la raza",
        "description": "Dia de la raza is a bank holiday in Guatemala",
        "country": {
          "id": "gt",
          "name": "Guatemala"
        },
        "date": {
          "iso": "2024-10-12",
          "datetime": {
            "year": 2024,
            "month": 10,
            "day": 12
          }
        },
        "type": [
          "National holiday"
        ],
        "primary_type": "Bank holiday",
        "canonical_url": "https://calendarific.com/holiday/guatemala/dia-de-la-raza",
        "urlid": "guatemala/dia-de-la-raza",
        "locations": "All",
        "states": "All"
      },
      {
        "name": "Revolution of 1944",
        "description": "Revolution of 1944 is a national holiday in Guatemala",
        "country": {
          "id": "gt",
          "name": "Guatemala"
        },
        "date": {
          "iso": "2024-10-20",
          "datetime": {
            "year": 2024,
            "month": 10,
            "day": 20
          }
        },
        "type": [
          "National holiday"
        ],
        "primary_type": "National holiday",
        "canonical_url": "https://calendarific.com/holiday/guatemala/revolution-of-1944",
        "urlid": "guatemala/revolution-of-1944",
        "locations": "All",
        "states": "All"
      },
      {
        "name": "All Saints' Day",
        "description": "Many churches honor all their saints on All Saints' Day, also known as All Hallows' Day.",
        "country": {
          "id": "gt",
          "name": "Guatemala"
        },
        "date": {
          "iso": "2024-11-01",
          "datetime": {
            "year": 2024,
            "month": 11,
            "day": 1
          }
        },
        "type": [
          "National holiday",
          "Christian"
        ],
        "primary_type": "Christian",
        "canonical_url": "https://calendarific.com/holiday/guatemala/all-saints-day",
        "urlid": "guatemala/all-saints-day",
        "locations": "All",
        "states": "All"
      },
      {
        "name": "December Solstice",
        "description": "December Solstice in Guatemala (Guatemala City)",
        "country": {
          "id": "gt",
          "name": "Guatemala"
        },
        "date": {
          "iso": "2024-12-21T03:20:34-06:00",
          "datetime": {
            "year": 2024,
            "month": 12,
            "day": 21,
            "hour": 3,
            "minute": 20,
            "second": 34
          },
          "timezone": {
            "offset": "-06:00",
            "zoneabb": "CST",
            "zoneoffset": -21600,
            "zonedst": 0,
            "zonetotaloffset": -21600
          }
        },
        "type": [
          "Season"
        ],
        "primary_type": "Season",
        "canonical_url": "https://calendarific.com/holiday/seasons/december-solstice",
        "urlid": "seasons/december-solstice",
        "locations": "All",
        "states": "All"
      },
      {
        "name": "Christmas Eve",
        "description": "Christmas Eve is the day before Christmas Day and falls on December 24 in the Gregorian calendar.",
        "country": {
          "id": "gt",
          "name": "Guatemala"
        },
        "date": {
          "iso": "2024-12-24",
          "datetime": {
            "year": 2024,
            "month": 12,
            "day": 24
          }
        },
        "type": [
          "National holiday"
        ],
        "primary_type": "Half day holiday",
        "canonical_url": "https://calendarific.com/holiday/guatemala/christmas-eve",
        "urlid": "guatemala/christmas-eve",
        "locations": "All",
        "states": "All"
      },
      {
        "name": "Christmas Day",
        "description": "Christmas Day is one of the biggest Christian celebrations and falls on December 25 in the Gregorian calendar.",
        "country": {
          "id": "gt",
          "name": "Guatemala"
        },
        "date": {
          "iso": "2024-12-25",
          "datetime": {
            "year": 2024,
            "month": 12,
            "day": 25
          }
        },
        "type": [
          "National holiday",
          "Christian"
        ],
        "primary_type": "Christian",
        "canonical_url": "https://calendarific.com/holiday/guatemala/christmas-day",
        "urlid": "guatemala/christmas-day",
        "locations": "All",
        "states": "All"
      },
      {
        "name": "New Year's Eve",
        "description": "New Year’s Eve is the last day of the year, December 31, in the Gregorian calendar.",
        "country": {
          "id": "gt",
          "name": "Guatemala"
        },
        "date": {
          "iso": "2024-12-31",
          "datetime": {
            "year": 2024,
            "month": 12,
            "day": 31
          }
        },
        "type": [
          "National holiday"
        ],
        "primary_type": "Half day holiday",
        "canonical_url": "https://calendarific.com/holiday/guatemala/new-years-eve",
        "urlid": "guatemala/new-years-eve",
        "locations": "All",
        "states": "All"
      }
    ]
  }
}