{
  "meta": {
    "code": 200
  },
  "response": {
    "holidays": [
      {
        "name": "New Year's Day",
        "description": "New Year’s Day is the first day of the year, or January 1, in the Gregorian calendar.",
        "country": {
          "id": "je",
          "name": "Jersey"
        },
        "date": {
          "iso": "2024-01-01",
          "datetime": {
            "year": 2024,
            "month": 1,
            "day": 1
          }
        },
        "type": [
          "National holiday"
        ],
        "primary_type": "Public Holiday",
        "canonical_url": "https://calendarific.com/holiday/jersey/new-year",
        "urlid": "jersey/new-year",
        "locations": "All",
        "states": "All"
      },
      {
        "name": "March Equinox",
        "description": "March Equinox in Jersey (Saint Helier)",
        "country": {
          "id": "je",
          "name": "Jersey"
        },
        "date": {
          "iso": "2024-03-20T03:06:28+00:00",
          "datetime": {
            "year": 2024,
            "month": 3,
            "day": 20,
            "hour": 3,
            "minute": 6,
            "second": 28
          },
          "timezone": {
            "offset": "+00:00",
            "zoneabb": "GMT",
            "zoneoffset": 0,
            "zonedst": 0,
            "zonetotaloffset": 0
          }
        },
        "type": [
          "Season"
        ],
        "primary_type": "Season",
        "canonical_url": "https://calendarific.com/holiday/seasons/vernal-equinox",
        "urlid": "seasons/vernal-equinox",
        "locations": "All",
        "states": "All"
      },
      {
        "name": "Good Friday",
        "description": "Good Friday is a global Christian observance two days before Easter Sunday.",
        "country": {
          "id": "je",
          "name": "Jersey"
        },
        "date": {
          "iso": "2024-03-29",
          "datetime": {
            "year": 2024,
            "month": 3,
            "day": 29
          }
        },
        "type": [
          "National holiday"
        ],
        "primary_type": "Public Holiday",
        "canonical_url": "https://calendarific.com/holiday/jersey/good-friday",
        "urlid": "jersey/good-friday",
        "locations": "All",
        "states": "All"
      },
      {
        "name": "Daylight Saving Time starts",
        "description": "Daylight Saving Time starts in Jersey",
        "country": {
          "id": "je",
          "name": "Jersey"
        },
        "date": {
          "iso": "2024-03-31T01:00:00+00:00",
          "datetime": {
            "year": 2024,
            "month": 3,
            "day": 31,
            "hour": 1,
            "minute": 0,
            "second": 0
          },
          "timezone": {
            "offset": "+00:00",
            "zoneabb": "GMT",
            "zoneoffset": 0,
            "zonedst": 0,
            "zonetotaloffset": 0
          }
        },
        "type": [
          "Clock change/Daylight Saving Time"
        ],
        "primary_type": "Clock change/Daylight Saving Time",
        "canonical_url": "https://calendarific.com/holiday/",
        "urlid": null,
        "locations": "All",
        "states": "All"
      },
      {
        "name": "Easter Monday",
        "description": "Easter Monday is the day after Easter Sunday.",
        "country": {
          "id": "je",
          "name": "Jersey"
        },
        "date": {
          "iso": "2024-04-01",
          "datetime": {
            "year": 2024,
            "month": 4,
            "day": 1
          }
        },
        "type": [
          "National holiday"
        ],
        "primary_type": "Public Holiday",
        "canonical_url": "https://calendarific.com/holiday/jersey/easter-monday",
        "urlid": "jersey/easter-monday",
        "locations": "All",
        "states": "All"
      },
      {
        "name": "Early May Bank Holiday",
        "description": "Labor Day, International Workers' Day, and May Day, is a day off for workers in many countries around the world.",
        "country": {
          "id": "je",
          "name": "Jersey"
        },
        "date": {
          "iso": "2024-05-06",
          "datetime": {
            "year": 2024,
            "month": 5,
            "day": 6
          }
        },
        "type": [
          "National holiday"
        ],
        "primary_type": "Public Holiday",
        "canonical_url": "https://calendarific.com/holiday/jersey/may-day",
        "urlid": "jersey/may-day",
        "locations": "All",
        "states": "All"
      },
      {
        "name": "Liberation Day",
        "description": "Liberation Day is a public holiday in Jersey",
        "country": {
          "id": "je",
          "name": "Jersey"
        },
        "date": {
          "iso": "2024-05-09",
          "datetime": {
            "year": 2024,
            "month": 5,
            "day": 9
          }
        },
        "type": [
          "National holiday"
        ],
        "primary_type": "Public Holiday",
        "canonical_url": "https://calendarific.com/holiday/jersey/liberation-day",
        "urlid": "jersey/liberation-day",
        "locations": "All",
        "states": "All"
      },
      {
        "name": "Spring Bank Holiday",
        "description": "Spring Bank Holiday is a public holiday in Jersey",
        "country": {
          "id": "je",
          "name": "Jersey"
        },
        "date": {
          "iso": "2024-05-27",
          "datetime": {
            "year": 2024,
            "month": 5,
            "day": 27
          }
        },
        "type": [
          "National holiday"
        ],
        "primary_type": "Public Holiday",
        "canonical_url": "https://calendarific.com/holiday/jersey/spring-bank-holiday",
        "urlid": "jersey/spring-bank-holiday",
        "locations": "All",
        "states": "All"
      },
      {
        "name": "June Solstice",
        "description": "June Solstice in Jersey (Saint Helier)",
        "country": {
          "id": "je",
          "name": "Jersey"
        },
        "date": {
          "iso": "2024-06-20T21:50:59+01:00",
          "datetime": {
            "year": 2024,
            "month": 6,
            "day": 20,
            "hour": 21,
            "minute": 50,
            "second": 59
          },
          "timezone": {
            "offset": "+01:00",
            "zoneabb": "BST",
            "zoneoffset": 0,
            "zonedst": 3600,
            "zonetotaloffset": 3600
          }
        },
        "type": [
          "Season"
        ],
        "primary_type": "Season",
        "canonical_url": "https://calendarific.com/holiday/seasons/june-solstice",
        "urlid": "seasons/june-solstice",
        "locations": "All",
        "states": "All"
      },
      {
        "name": "Summer Bank Holiday",
        "description": "Summer Bank Holiday is a public holiday in Jersey",
        "country": {
          "id": "je",
          "name": "Jersey"
        },
        "date": {
          "iso": "2024-08-26",
          "datetime": {
            "year": 2024,
            "month": 8,
            "day": 26
          }
        },
        "type": [
          "National holiday"
        ],
        "primary_type": "Public Holiday",
        "canonical_url": "https://calendarific.com/holiday/jersey/summer-bank-holiday",
        "urlid": "jersey/summer-bank-holiday",
        "locations": "All",
        "states": "All"
      },
      {
        "name": "September Equinox",
        "description": "September Equinox in Jersey (Saint Helier)",
        "country": {
          "id": "je",
          "name": "Jersey"
        },
        "date": {
          "iso": "2024-09-22T13:43:33+01:00",
          "datetime": {
            "year": 2024,
            "month": 9,
            "day": 22,
            "hour": 13,
            "minute": 43,
            "second": 33
          },
          "timezone": {
            "offset": "+01:00",
            "zoneabb": "BST",
            "zoneoffset": 0,
            "zonedst": 3600,
            "zonetotaloffset": 3600
          }
        },
        "type": [
          "Season"
        ],
        "primary_type": "Season",
        "canonical_url": "https://calendarific.com/holiday/seasons/autumnal-equniox",
        "urlid": "seasons/autumnal-equniox",
        "locations": "All",
        "states": "All"
      },
      {
        "name": "Daylight Saving Time ends",
        "description": "Daylight Saving Time ends in Jersey",
        "country": {
          "id": "je",
          "name": "Jersey"
        },
        "date": {
          "iso": "2024-10-27T02:00:00+01:00",
          "datetime": {
            "year": 2024,
            "month": 10,
            "day": 27,
            "hour": 2,
            "minute": 0,
            "second": 0
          },
          "timezone": {
            "offset": "+01:00",
            "zoneabb": "BST",
            "zoneoffset": 0,
            "zonedst": 3600,
            "zonetotaloffset": 3600
          }
        },
        "type": [
          "Clock change/Daylight Saving Time"
        ],
        "primary_type": "Clock change/Daylight Saving Time",
        "canonical_url": "https://calendarific.com/holiday/",
        "urlid": null,
        "locations": "All",
        "states": "All"
      },
      {
        "name": "December Solstice",
        "description": "December Solstice in Jersey (Saint Helier)",
        "country": {
          "id": "je",
          "name": "Jersey"
        },
        "date": {
          "iso": "2024-12-21T09:20:34+00:00",
          "datetime": {
            "year": 2024,
            "month": 12,
            "day": 21,
            "hour": 9,
            "minute": 20,
            "second": 34
          },
          "timezone": {
            "offset": "+00:00",
            "zoneabb": "GMT",
            "zoneoffset": 0,
            "zonedst": 0,
            "zonetotaloffset": 0
          }
        },
        "type": [
          "Season"
        ],
        "primary_type": "Season",
        "canonical_url": "https://calendarific.com/holiday/seasons/december-solstice",
        "urlid": "seasons/december-solstice",
        "locations": "All",
        "states": "All"
      },
      {
        "name": "Christmas Day",
        "description": "Christmas Day is one of the biggest Christian celebrations and falls on December 25 in the Gregorian calendar.",
        "country": {
          "id": "je",
          "name": "Jersey"
        },
        "date": {
          "iso": "2024-12-25",
          "datetime": {
            "year": 2024,
            "month": 12,
            "day": 25
          }
        },
        "type": [
          "National holiday"
        ],
        "primary_type": "Public Holiday",
        "canonical_url": "https://calendarific.com/holiday/jersey/christmas-day",
        "urlid": "jersey/christmas-day",
        "locations": "All",
        "states": "All"
      },
      {
        "name": "Boxing Day",
        "description": "Boxing Day is a public holiday in Jersey",
        "country": {
          "id": "je",
          "name": "Jersey"
        },
        "date": {
          "iso": "2024-12-26",
          "datetime": {
            "year": 2024,
            "month": 12,
            "day": 26
          }
        },
        "type": [
          "National holiday"
        ],
        "primary_type": "Public Holiday",
        "canonical_url": "https://calendarific.com/holiday/jersey/second-day-of-christmas",
        "urlid": "jersey/second-day-of-christmas",
        "locations": "All",
        "states": "All"
      }
    ]
  }
}